darkcore/__init__.py
darkcore/core.py
darkcore/either.py
darkcore/either_t.py
darkcore/maybe.py
darkcore/maybe_t.py
darkcore/py.typed
darkcore/reader.py
darkcore/reader_t.py
darkcore/result.py
darkcore/result_t.py
darkcore/rwst.py
darkcore/state.py
darkcore/state_t.py
darkcore/traverse.py
darkcore/validation.py
darkcore/validation_t.py
darkcore/writer.py
darkcore/writer_t.py
darkcore-0.5.1.dist-info/LICENSE
darkcore-0.5.1.dist-info/METADATA
darkcore-0.5.1.dist-info/WHEEL
darkcore-0.5.1.dist-info/RECORD
