Metadata-Version: 2.3
Name: darkcore
Version: 0.5.1
Summary: Practical functional programming primitives for Python: Monads, Transformers, and DSL operators for safe business logic
License: MIT
Keywords: monad,functional,dsl,business logic
Author: minamorl
Author-email: minamorl@users.noreply.github.com
Requires-Python: >=3.10,<3.13
Classifier: License :: OSI Approved :: MIT License
Classifier: Programming Language :: Python :: 3
Classifier: Programming Language :: Python :: 3.10
Classifier: Programming Language :: Python :: 3.11
Classifier: Programming Language :: Python :: 3.12
Project-URL: Homepage, https://github.com/minamorl/darkcore
Project-URL: Repository, https://github.com/minamorl/darkcore
